mysql_pool/__init__.py
mysql_pool/base.py
mysql_pool/client.py
mysql_pool/compiler.py
mysql_pool/creation.py
mysql_pool/features.py
mysql_pool/introspection.py
mysql_pool/operations.py
mysql_pool/schema.py
mysql_pool/validation.py
django_mysql_pool_by_pramod-1.0.0.dist-info/METADATA
django_mysql_pool_by_pramod-1.0.0.dist-info/WHEEL
django_mysql_pool_by_pramod-1.0.0.dist-info/top_level.txt
django_mysql_pool_by_pramod-1.0.0.dist-info/RECORD
